rational/__init__.py
rational/cuda.cpython-36m-x86_64-linux-gnu.so
rational/rationals_config.json
rational/_base/__init__.py
rational/_base/rational_base.py
rational/_cuda/rational_cuda.cpp
rational/_cuda/rational_cuda_kernels.cu
rational/keras/__init__.py
rational/keras/rationals.py
rational/keras/versions.py
rational/mxnet/__init__.py
rational/mxnet/rationals.py
rational/mxnet/versions.py
rational/numpy/__init__.py
rational/numpy/rationals.py
rational/torch/__init__.py
rational/torch/rational_cuda_functions.py
rational/torch/rational_pytorch_functions.py
rational/torch/rationals.py
rational/utils/__init__.py
rational/utils/convert_network.py
rational/utils/find_init_weights.py
rational/utils/get_weights.py
rational/utils/histograms_cupy.py
rational/utils/histograms_numpy.py
rational/utils/utils.py
rational/utils/warnings.py
rational_activations.libs/libcudart.so.11.1.74
rational_activations-0.2.1.dist-info/LICENSE
rational_activations-0.2.1.dist-info/METADATA
rational_activations-0.2.1.dist-info/WHEEL
rational_activations-0.2.1.dist-info/top_level.txt
rational_activations-0.2.1.dist-info/RECORD
