Metadata-Version: 2.1
Name: rational-activations
Version: 0.2.1
Summary: Rational Activations
Home-page: https://github.com/ml-research/rational_activations
Author: Alejandro Molina, Quentin Delfosse, Patrick Schramowski
Author-email: molina@cs.tu-darmstadt.de, quentin.delfosse@cs.tu-darmstadt.de
License: UNKNOWN
Platform: UNKNOWN
Classifier: Programming Language :: Python :: 3
Classifier: Programming Language :: Python :: 3.6
Classifier: Programming Language :: Python :: 3.7
Classifier: Programming Language :: Python :: 3.8
Classifier: License :: OSI Approved :: Apache Software License
Requires-Python: >=3.5.0
Requires-Dist: numpy
Requires-Dist: scipy
Requires-Dist: matplotlib
Requires-Dist: torch (==1.9.0)
Requires-Dist: tqdm
Requires-Dist: termcolor
